{
  "profil": {
    "kode": "ARCI",
    "nama": "PT Archi Indonesia Tbk",
    "sektor": "Basic Materials",
    "sub_sektor": "Gold",
    "deskripsi_bisnis": "PT Archi Indonesia Tbk, through its subsidiaries, engages in gold and silver mining business in Indonesia. The company operates Toka Tindung Gold Mine with the concession area of approximately 40 thousand hectares located in North Sulawesi. It also holds contracts of work for mining concession areas with a total concession area of 39,817 hectares located in North Sulawesi Province. In addition, the company provides mining contractor services; gold minted bar products; and management consulting services. The company was incorporated in 2010 and is headquartered in Jakarta Selatan, Indonesia. PT Archi Indonesia Tbk is a subsidiary of PT Rajawali Corporation.",
    "manajemen": "",
    "keunggulan_kompetitif": "",
    "prospek_industri": "",
    "berita_terkini": "⚠️ Laporan keuangan dalam USD, harga dalam IDR. Rasio (ROE/ROA/margin) tetap valid, tetapi valuasi per-saham (EPS/PER/PBV/DCF) tidak akurat tanpa konversi kurs."
  },
  "laporan": [
    {
      "tahun": 2022,
      "total_aset": 717816422.0,
      "aset_lancar": 87174516.0,
      "total_liabilitas": 470060983.0,
      "liabilitas_lancar": 201502683.0,
      "total_ekuitas": 247837925.0,
      "pendapatan": 216476272.0,
      "laba_kotor": 59530464.0,
      "laba_operasi": 41548632.0,
      "laba_bersih": 14550684.0,
      "arus_kas_operasi": 0.0,
      "arus_kas_investasi": -69344752.0,
      "arus_kas_pendanaan": 13676772.0
    },
    {
      "tahun": 2023,
      "total_aset": 803580181.0,
      "aset_lancar": 94562276.0,
      "total_liabilitas": 540950196.0,
      "liabilitas_lancar": 122160820.0,
      "total_ekuitas": 262534900.0,
      "pendapatan": 249630768.0,
      "laba_kotor": 69769695.0,
      "laba_operasi": 56088034.0,
      "laba_bersih": 14569739.0,
      "arus_kas_operasi": 0.0,
      "arus_kas_investasi": -122294351.0,
      "arus_kas_pendanaan": 99996711.0
    },
    {
      "tahun": 2024,
      "total_aset": 865399797.0,
      "aset_lancar": 92788106.0,
      "total_liabilitas": 592443636.0,
      "liabilitas_lancar": 184637191.0,
      "total_ekuitas": 272906015.0,
      "pendapatan": 287618877.0,
      "laba_kotor": 60523621.0,
      "laba_operasi": 53456824.0,
      "laba_bersih": 10457653.0,
      "arus_kas_operasi": 0.0,
      "arus_kas_investasi": -91757559.0,
      "arus_kas_pendanaan": -2972248.0
    },
    {
      "tahun": 2025,
      "total_aset": 1026763377.0,
      "aset_lancar": 172120458.0,
      "total_liabilitas": 663835665.0,
      "liabilitas_lancar": 161301440.0,
      "total_ekuitas": 362190321.0,
      "pendapatan": 496229823.0,
      "laba_kotor": 210044397.0,
      "laba_operasi": 201377475.0,
      "laba_bersih": 101821019.0,
      "arus_kas_operasi": 0.0,
      "arus_kas_investasi": -105186924.0,
      "arus_kas_pendanaan": 73224768.0
    }
  ],
  "pasar": {
    "harga_saham": 1095.0,
    "saham_beredar": 25235000000.0,
    "per_sektor": null,
    "pbv_sektor": null,
    "mean_per_3y": null,
    "mean_pbv_3y": null,
    "growth_rate": 0.08,
    "discount_rate": 0.11,
    "terminal_growth": 0.03,
    "tahun_proyeksi": 5,
    "dividend_yield": 0.020485148514851486,
    "dividen_per_saham": 20.69,
    "dividen_beruntun": 2
  },
  "backtest": {
    "s1": {
      "sinyal": 59,
      "menang": 34,
      "hit3": 0,
      "ret_total": -0.0021734955556905935,
      "sinyal_terakhir": false
    },
    "s2": {
      "sinyal": 6,
      "menang": 4,
      "hit3": 0,
      "ret_total": -0.011006849763814249,
      "sinyal_terakhir": false
    },
    "s3": {
      "sinyal": 19,
      "menang": 18,
      "hit3": 3,
      "ret_total": 0.2534320142184874,
      "sinyal_terakhir": false
    },
    "s_and": {
      "sinyal": 0,
      "menang": 0,
      "hit3": 0,
      "ret_total": 0.0,
      "sinyal_terakhir": false
    },
    "s_or": {
      "sinyal": 65,
      "menang": 38,
      "hit3": 0,
      "ret_total": -0.013180345319504853,
      "sinyal_terakhir": false
    }
  },
  "harian": {
    "sampel_hari": 252,
    "peluang_naik_target": 0.0992063492063492,
    "win_rate": 0.5634920634920635,
    "rata_gap": 0.0042268735632133795,
    "median_gap": 5.707120582911338e-08,
    "rata_gap_positif": 0.018162585808250864,
    "volatilitas_gap": 0.024895803452746477,
    "volume_rata": 112103723.32015811,
    "target": 0.03
  }
}