{
  "profil": {
    "kode": "DART",
    "nama": "PT Duta Anggada Realty Tbk.",
    "sektor": "Real Estate",
    "sub_sektor": "Real Estate Services",
    "deskripsi_bisnis": "PT Duta Anggada Realty Tbk. engages in the real estate development activities in Indonesia. The company develops, sells, rents, and manages residential apartments, office buildings, shopping centres, and hotels. It also provides tourism hospitality services. The company was formerly known as PT Duta Anggada Inti Pratama and changed its name to PT Duta Anggada Realty Tbk. in April 1997. PT Duta Anggada Realty Tbk. was founded in 1983 and is headquartered in Jakarta, Indonesia.",
    "manajemen": "",
    "keunggulan_kompetitif": "",
    "prospek_industri": "",
    "berita_terkini": ""
  },
  "laporan": [
    {
      "tahun": 2022,
      "total_aset": 6462680097000.0,
      "aset_lancar": 142287400000.0,
      "total_liabilitas": 4380333825000.0,
      "liabilitas_lancar": 995858912000.0,
      "total_ekuitas": 2082368700000.0,
      "pendapatan": 330155372000.0,
      "laba_kotor": 101038796000.0,
      "laba_operasi": -35598779000.0,
      "laba_bersih": -421148843000.0,
      "arus_kas_operasi": 0.0,
      "arus_kas_investasi": -34820510000.0,
      "arus_kas_pendanaan": 72409656000.0
    },
    {
      "tahun": 2023,
      "total_aset": 6316969636000.0,
      "aset_lancar": 124122818000.0,
      "total_liabilitas": 4578440529000.0,
      "liabilitas_lancar": 823597854000.0,
      "total_ekuitas": 1738556575000.0,
      "pendapatan": 433200487000.0,
      "laba_kotor": 182044426000.0,
      "laba_operasi": 28520691000.0,
      "laba_bersih": -343792492000.0,
      "arus_kas_operasi": 0.0,
      "arus_kas_investasi": -7823168000.0,
      "arus_kas_pendanaan": -25134945000.0
    },
    {
      "tahun": 2024,
      "total_aset": 6208681516000.0,
      "aset_lancar": 131682599000.0,
      "total_liabilitas": 4766522099000.0,
      "liabilitas_lancar": 1310521180000.0,
      "total_ekuitas": 1442189540000.0,
      "pendapatan": 511558731000.0,
      "laba_kotor": 237094360000.0,
      "laba_operasi": 64336243000.0,
      "laba_bersih": -296799024000.0,
      "arus_kas_operasi": 0.0,
      "arus_kas_investasi": -3251929000.0,
      "arus_kas_pendanaan": -42773867000.0
    },
    {
      "tahun": 2025,
      "total_aset": 6103393716000.0,
      "aset_lancar": 129444878000.0,
      "total_liabilitas": 4921720215000.0,
      "liabilitas_lancar": 3055991785000.0,
      "total_ekuitas": 1181705829000.0,
      "pendapatan": 507155984000.0,
      "laba_kotor": 234972331000.0,
      "laba_operasi": 88824121000.0,
      "laba_bersih": -259619237000.0,
      "arus_kas_operasi": 0.0,
      "arus_kas_investasi": 9253946000.0,
      "arus_kas_pendanaan": -49395340000.0
    }
  ],
  "pasar": {
    "harga_saham": 121.0,
    "saham_beredar": 3141390962.0,
    "per_sektor": null,
    "pbv_sektor": null,
    "mean_per_3y": null,
    "mean_pbv_3y": null,
    "growth_rate": 0.08,
    "discount_rate": 0.11,
    "terminal_growth": 0.03,
    "tahun_proyeksi": 5
  }
}