{
  "profil": {
    "kode": "FAST",
    "nama": "PT Fast Food Indonesia Tbk",
    "sektor": "Consumer Cyclical",
    "sub_sektor": "Restaurants",
    "deskripsi_bisnis": "PT Fast Food Indonesia Tbk engages in the food and restaurant activities in Indonesia. It holds rights to establish and operate Kentucky Fried Chicken and Taco Bell franchise outlets. The company was incorporated in 1978 and is headquartered in Jakarta, Indonesia.",
    "manajemen": "",
    "keunggulan_kompetitif": "",
    "prospek_industri": "",
    "berita_terkini": ""
  },
  "laporan": [
    {
      "tahun": 2021,
      "total_aset": 3501061386000.0,
      "aset_lancar": 1178139902000.0,
      "total_liabilitas": 2383578094000.0,
      "liabilitas_lancar": 1400609966000.0,
      "total_ekuitas": 1117483292000.0,
      "pendapatan": 4840596018000.0,
      "laba_kotor": 2935820140000.0,
      "laba_operasi": -324915474000.0,
      "laba_bersih": -300609572000.0,
      "arus_kas_operasi": 0.0,
      "arus_kas_investasi": -273879871000.0,
      "arus_kas_pendanaan": 9825294000.0
    },
    {
      "tahun": 2022,
      "total_aset": 3822405039000.0,
      "aset_lancar": 1272159970000.0,
      "total_liabilitas": 2761382295000.0,
      "liabilitas_lancar": 1606887945000.0,
      "total_ekuitas": 1061022744000.0,
      "pendapatan": 5857474313000.0,
      "laba_kotor": 3664728148000.0,
      "laba_operasi": -23377281000.0,
      "laba_bersih": -77447669000.0,
      "arus_kas_operasi": 0.0,
      "arus_kas_investasi": -341394707000.0,
      "arus_kas_pendanaan": 19640159000.0
    },
    {
      "tahun": 2023,
      "total_aset": 3910544291000.0,
      "aset_lancar": 947542386000.0,
      "total_liabilitas": 3186666815000.0,
      "liabilitas_lancar": 1971043945000.0,
      "total_ekuitas": 711729655000.0,
      "pendapatan": 5935004692000.0,
      "laba_kotor": 3665397401000.0,
      "laba_operasi": -284505093000.0,
      "laba_bersih": -415654980000.0,
      "arus_kas_operasi": 0.0,
      "arus_kas_investasi": -712019441000.0,
      "arus_kas_pendanaan": -15564526000.0
    },
    {
      "tahun": 2024,
      "total_aset": 3529220278000.0,
      "aset_lancar": 616598946000.0,
      "total_liabilitas": 3401488684000.0,
      "liabilitas_lancar": 2291914466000.0,
      "total_ekuitas": 48365013000.0,
      "pendapatan": 4875792516000.0,
      "laba_kotor": 2840833951000.0,
      "laba_operasi": -697667810000.0,
      "laba_bersih": -796711869000.0,
      "arus_kas_operasi": 0.0,
      "arus_kas_investasi": -293618610000.0,
      "arus_kas_pendanaan": 248319000.0
    }
  ],
  "pasar": {
    "harga_saham": 284.0,
    "saham_beredar": 4520402492.0,
    "per_sektor": null,
    "pbv_sektor": null,
    "mean_per_3y": null,
    "mean_pbv_3y": null,
    "growth_rate": 0.08,
    "discount_rate": 0.11,
    "terminal_growth": 0.03,
    "tahun_proyeksi": 5,
    "dividend_yield": 0.057971014492753624,
    "dividen_per_saham": 16.0,
    "dividen_beruntun": 19
  },
  "backtest": {
    "s1": {
      "sinyal": 3,
      "menang": 1,
      "hit3": 0,
      "ret_total": 0.012711864406779662,
      "sinyal_terakhir": false
    },
    "s2": {
      "sinyal": 3,
      "menang": 2,
      "hit3": 0,
      "ret_total": 0.024259113558877526,
      "sinyal_terakhir": false
    },
    "s3": {
      "sinyal": 4,
      "menang": 3,
      "hit3": 3,
      "ret_total": 0.3787432575674504,
      "sinyal_terakhir": false
    },
    "s_and": {
      "sinyal": 0,
      "menang": 0,
      "hit3": 0,
      "ret_total": 0.0,
      "sinyal_terakhir": false
    },
    "s_or": {
      "sinyal": 6,
      "menang": 3,
      "hit3": 0,
      "ret_total": 0.03697097796565719,
      "sinyal_terakhir": false
    }
  },
  "harian": {
    "sampel_hari": 252,
    "peluang_naik_target": 0.0992063492063492,
    "win_rate": 0.45634920634920634,
    "rata_gap": 0.007232901728307347,
    "median_gap": 0.0,
    "rata_gap_positif": 0.026803385709543687,
    "volatilitas_gap": 0.03663413254987911,
    "volume_rata": 16148743.47826087,
    "target": 0.03
  }
}