{
  "profil": {
    "kode": "FWCT",
    "nama": "PT Wijaya Cahaya Timber Tbk",
    "sektor": "Basic Materials",
    "sub_sektor": "Lumber & Wood Production",
    "deskripsi_bisnis": "PT Wijaya Cahaya Timber Tbk manufactures and sells plywood products for industrial and residential needs in Indonesia. The company offers falcata, meranti/mixed light hardwood, white and natural birch, and veneer products. It also engages in the manufacture of ordinary plywood, such as plywood, multiply, interior, exterior, and related products, as well as coating shavings. In addition, the company provides management consulting services. Further, it engages in industry, trading, and shipping activities. PT Wijaya Cahaya Timber Tbk was founded in 2017 and is headquartered in Jakarta Barat, Indonesia.",
    "manajemen": "",
    "keunggulan_kompetitif": "",
    "prospek_industri": "",
    "berita_terkini": ""
  },
  "laporan": [],
  "pasar": {
    "harga_saham": 100.0,
    "saham_beredar": 1963000000.0,
    "per_sektor": null,
    "pbv_sektor": null,
    "mean_per_3y": null,
    "mean_pbv_3y": null,
    "growth_rate": 0.08,
    "discount_rate": 0.11,
    "terminal_growth": 0.03,
    "tahun_proyeksi": 5,
    "dividend_yield": 0.0898876404494382,
    "dividen_per_saham": 8.0,
    "dividen_beruntun": 3
  },
  "backtest": {
    "s1": {
      "sinyal": 0,
      "menang": 0,
      "hit3": 0,
      "ret_total": 0.0,
      "sinyal_terakhir": false
    },
    "s2": {
      "sinyal": 4,
      "menang": 3,
      "hit3": 0,
      "ret_total": 0.042549731775699706,
      "sinyal_terakhir": false
    },
    "s_and": {
      "sinyal": 0,
      "menang": 0,
      "hit3": 0,
      "ret_total": 0.0,
      "sinyal_terakhir": false
    },
    "s_or": {
      "sinyal": 4,
      "menang": 3,
      "hit3": 0,
      "ret_total": 0.042549731775699706,
      "sinyal_terakhir": false
    }
  },
  "harian": {
    "sampel_hari": 252,
    "peluang_naik_target": 0.01984126984126984,
    "win_rate": 0.3492063492063492,
    "rata_gap": 0.0031228294047112976,
    "median_gap": 0.0,
    "rata_gap_positif": 0.014349623994906436,
    "volatilitas_gap": 0.014186133754778622,
    "volume_rata": 9254616.205533598,
    "target": 0.03
  }
}