{
  "profil": {
    "kode": "LMPI",
    "nama": "PT Langgeng Makmur Industri Tbk",
    "sektor": "Consumer Cyclical",
    "sub_sektor": "Furnishings, Fixtures & Appliances",
    "deskripsi_bisnis": "PT Langgeng Makmur Industri Tbk manufactures and sells aluminum kitchenware, plastic houseware, pipes, fittings, and profiles in Asia, the Middle East, and internationally. The company operates through Aluminium Cookware; PVC Pipes, Fittings and Profiles; and Plastic Houseware and Others segments. It offers aluminum kitchenware products comprising pots, woks, kettles, polished rice containers, basins, and other products; and plastic houseware products, such as container and storage, food service, kitchen and bathroom, and household products, as well as pails and basins. The company also provides nonstick cookware and bakeware products; and PVC and PE pipes, PVC fittings, and PVC profiles comprising rain gutter and water hose. The company was formerly known as PT Langgeng Makmur Plastic Industry Ltd. and changed its name to PT Langgeng Makmur Industri Tbk in July 1997. The company was founded in 1972 and is headquartered in Sidoarjo, Indonesia.",
    "manajemen": "",
    "keunggulan_kompetitif": "",
    "prospek_industri": "",
    "berita_terkini": ""
  },
  "laporan": [],
  "pasar": {
    "harga_saham": 138.0,
    "saham_beredar": 1008517669.0,
    "per_sektor": null,
    "pbv_sektor": null,
    "mean_per_3y": null,
    "mean_pbv_3y": null,
    "growth_rate": 0.08,
    "discount_rate": 0.11,
    "terminal_growth": 0.03,
    "tahun_proyeksi": 5,
    "dividend_yield": null,
    "dividen_per_saham": null,
    "dividen_beruntun": 0
  },
  "harian": {
    "sampel_hari": 252,
    "peluang_naik_target": 0.051587301587301584,
    "win_rate": 0.376984126984127,
    "rata_gap": 0.003166154195694095,
    "median_gap": 0.0,
    "rata_gap_positif": 0.019613089027525336,
    "volatilitas_gap": 0.02520061988354758,
    "volume_rata": 1291904.347826087,
    "target": 0.03
  }
}