{
  "profil": {
    "kode": "MKAP",
    "nama": "Multikarya Asia Pasifik Raya Tb",
    "sektor": "Energy",
    "sub_sektor": "Oil & Gas Equipment & Services",
    "deskripsi_bisnis": "PT Multikarya Asia Pasifik Raya Tbk provides products and services to the oil and gas industry in Indonesia and Southeast Asia. It provides rental, repair/recertification, maintenance, machining, and general trading services. The company also offers reciprocating, centrifugal, and screw pumps; mud pump part and expendables, centrifugal pump parts, butterfly valves, gate valves, and handling tools; solid control equipment; gas and diesel engine power generation sets; and wellhead compressors. PT Multikarya Asia Pasifik Raya Tbk was founded in 2002 and is headquartered in Jakarta Selatan, Indonesia. The company operates as a subsidiary of PT International Sawo Resources.",
    "manajemen": "",
    "keunggulan_kompetitif": "",
    "prospek_industri": "",
    "berita_terkini": ""
  },
  "laporan": [
    {
      "tahun": 2021,
      "total_aset": 258295431730.0,
      "aset_lancar": 133290608875.0,
      "total_liabilitas": 119021110680.0,
      "liabilitas_lancar": 87250335474.0,
      "total_ekuitas": 139274321050.0,
      "pendapatan": 111964057107.0,
      "laba_kotor": 30680859604.0,
      "laba_operasi": 8014588217.0,
      "laba_bersih": 15019538975.0,
      "arus_kas_operasi": 0.0,
      "arus_kas_investasi": 0.0,
      "arus_kas_pendanaan": 0.0
    },
    {
      "tahun": 2022,
      "total_aset": 237946928859.0,
      "aset_lancar": 154337456679.0,
      "total_liabilitas": 105774878718.0,
      "liabilitas_lancar": 100665145563.0,
      "total_ekuitas": 132172050141.0,
      "pendapatan": 195008507024.0,
      "laba_kotor": 56703612568.0,
      "laba_operasi": 17817852858.0,
      "laba_bersih": -1654741665.0,
      "arus_kas_operasi": 0.0,
      "arus_kas_investasi": 0.0,
      "arus_kas_pendanaan": 0.0
    },
    {
      "tahun": 2024,
      "total_aset": 519155497750.0,
      "aset_lancar": 365947029847.0,
      "total_liabilitas": 241401488453.0,
      "liabilitas_lancar": 209342672228.0,
      "total_ekuitas": 277754009297.0,
      "pendapatan": 356262936436.0,
      "laba_kotor": 126995090883.0,
      "laba_operasi": 70409725631.0,
      "laba_bersih": 40675272205.0,
      "arus_kas_operasi": 0.0,
      "arus_kas_investasi": 0.0,
      "arus_kas_pendanaan": 0.0
    },
    {
      "tahun": 2025,
      "total_aset": 536122410763.0,
      "aset_lancar": 366268878887.0,
      "total_liabilitas": 212748732573.0,
      "liabilitas_lancar": 178337829690.0,
      "total_ekuitas": 323373678190.0,
      "pendapatan": 405636314904.0,
      "laba_kotor": 135479225711.0,
      "laba_operasi": 70601025326.0,
      "laba_bersih": 55344177173.0,
      "arus_kas_operasi": 0.0,
      "arus_kas_investasi": 0.0,
      "arus_kas_pendanaan": 0.0
    }
  ],
  "pasar": {
    "harga_saham": 1170.0,
    "saham_beredar": 3250000000.0,
    "per_sektor": null,
    "pbv_sektor": null,
    "mean_per_3y": null,
    "mean_pbv_3y": null,
    "growth_rate": 0.08,
    "discount_rate": 0.11,
    "terminal_growth": 0.03,
    "tahun_proyeksi": 5,
    "dividend_yield": 0.004273504273504274,
    "dividen_per_saham": 5.0,
    "dividen_beruntun": 2
  },
  "backtest": {
    "s1": {
      "sinyal": 7,
      "menang": 4,
      "hit3": 0,
      "ret_total": 0.007751890036681067,
      "sinyal_terakhir": false
    },
    "s2": {
      "sinyal": 5,
      "menang": 2,
      "hit3": 1,
      "ret_total": 0.050847364231725756,
      "sinyal_terakhir": false
    },
    "s_and": {
      "sinyal": 0,
      "menang": 0,
      "hit3": 0,
      "ret_total": 0.0,
      "sinyal_terakhir": false
    },
    "s_or": {
      "sinyal": 12,
      "menang": 6,
      "hit3": 1,
      "ret_total": 0.05859925426840683,
      "sinyal_terakhir": false
    }
  },
  "harian": {
    "sampel_hari": 252,
    "peluang_naik_target": 0.007936507936507936,
    "win_rate": 0.30158730158730157,
    "rata_gap": -0.0011871975417972291,
    "median_gap": 0.0,
    "rata_gap_positif": 0.004677993553308374,
    "volatilitas_gap": 0.014591488084605224,
    "volume_rata": 1181955.3359683794,
    "target": 0.03
  }
}