{
  "profil": {
    "kode": "NANO",
    "nama": "PT Nanotech Indonesia Global Tbk",
    "sektor": "Healthcare",
    "sub_sektor": "Medical Devices",
    "deskripsi_bisnis": "PT Nanotech Indonesia Global Tbk provides technology and engineering research and development services in Indonesia. The company operates in two segments, Service and Trading. It engages in travel agencies, bureau, tourism, nature tourism information, management consulting, employment, and education businesses, as well as operates in the manufacturing and trading industries. The company was incorporated in 2019 and is headquartered in South Tangerang, Indonesia. PT Nanotech Indonesia Global Tbk is a subsidiary of PT Nanotech Investama Sedaya.",
    "manajemen": "",
    "keunggulan_kompetitif": "",
    "prospek_industri": "",
    "berita_terkini": ""
  },
  "laporan": [],
  "pasar": {
    "harga_saham": 36.0,
    "saham_beredar": 4285233928.0,
    "per_sektor": null,
    "pbv_sektor": null,
    "mean_per_3y": null,
    "mean_pbv_3y": null,
    "growth_rate": 0.08,
    "discount_rate": 0.11,
    "terminal_growth": 0.03,
    "tahun_proyeksi": 5,
    "dividend_yield": null,
    "dividen_per_saham": null,
    "dividen_beruntun": 0
  },
  "backtest": {
    "s1": {
      "sinyal": 0,
      "menang": 0,
      "hit3": 0,
      "ret_total": 0.0,
      "sinyal_terakhir": false
    },
    "s2": {
      "sinyal": 2,
      "menang": 1,
      "hit3": 0,
      "ret_total": 0.017543859649122806,
      "sinyal_terakhir": false
    },
    "s_and": {
      "sinyal": 0,
      "menang": 0,
      "hit3": 0,
      "ret_total": 0.0,
      "sinyal_terakhir": false
    },
    "s_or": {
      "sinyal": 2,
      "menang": 1,
      "hit3": 0,
      "ret_total": 0.017543859649122806,
      "sinyal_terakhir": false
    }
  },
  "harian": {
    "sampel_hari": 252,
    "peluang_naik_target": 0.15476190476190477,
    "win_rate": 0.2619047619047619,
    "rata_gap": 0.005364103187100775,
    "median_gap": 0.0,
    "rata_gap_positif": 0.043616706454769436,
    "volatilitas_gap": 0.03105183433214374,
    "volume_rata": 40046585.37549407,
    "target": 0.03
  }
}