{
  "profil": {
    "kode": "NELY",
    "nama": "PT Pelayaran Nelly Dwi Putri Tbk",
    "sektor": "Industrials",
    "sub_sektor": "Marine Shipping",
    "deskripsi_bisnis": "PT Pelayaran Nelly Dwi Putri Tbk provides shipping services in Indonesia. It operates through Vessel leasing services (Charter), Shipyard & Engineering, and Others segments. The company offers ship rental services, such as freight and time charter systems and shipping consulting services. It also provides shipbuilding, maintenance, and repair services, as well as engages in tugboats, barge, and container ship, and shipyard activities. In addition, the company engages in domestic and international shipping, sea, and transportation services for general and special goods; manufacturing, maintenance, and repair of tugs and barges; power generation electricity, alternative and gas power generation industry; shipping; oil and gas transportation, and marine vessel rental services; chartering of ships and vessels; wholesale and retail trade, repair and maintenance of motor vehicles and motorcycles; manufacturing; electricity supply; and construction. PT Pelayaran Nelly Dwi Putri Tbk was incorporated in 1977 and is based in Jakarta Pusat, Indonesia. PT Pelayaran Nelly Dwi Putri Tbk operates as a subsidiary of PT Haskojaya Abadi.",
    "manajemen": "",
    "keunggulan_kompetitif": "",
    "prospek_industri": "",
    "berita_terkini": ""
  },
  "laporan": [],
  "pasar": {
    "harga_saham": NaN,
    "saham_beredar": 2350000000.0,
    "per_sektor": null,
    "pbv_sektor": null,
    "mean_per_3y": null,
    "mean_pbv_3y": null,
    "growth_rate": 0.08,
    "discount_rate": 0.11,
    "terminal_growth": 0.03,
    "tahun_proyeksi": 5,
    "dividend_yield": 0.04807692307692308,
    "dividen_per_saham": 10.0,
    "dividen_beruntun": 14
  },
  "backtest": {
    "s1": {
      "sinyal": 6,
      "menang": 5,
      "hit3": 0,
      "ret_total": 0.014545571944328557,
      "sinyal_terakhir": false
    },
    "s2": {
      "sinyal": 2,
      "menang": 2,
      "hit3": 0,
      "ret_total": 0.021305254046027015,
      "sinyal_terakhir": false
    },
    "s_and": {
      "sinyal": 0,
      "menang": 0,
      "hit3": 0,
      "ret_total": 0.0,
      "sinyal_terakhir": false
    },
    "s_or": {
      "sinyal": 8,
      "menang": 7,
      "hit3": 0,
      "ret_total": 0.035850825990355564,
      "sinyal_terakhir": false
    }
  },
  "harian": {
    "sampel_hari": 251,
    "peluang_naik_target": 0.027888446215139442,
    "win_rate": 0.5737051792828686,
    "rata_gap": 0.0031757741415547654,
    "median_gap": 2.0897628429674026e-08,
    "rata_gap_positif": 0.008197614502699355,
    "volatilitas_gap": 0.011862802510305618,
    "volume_rata": 2302772.33201581,
    "target": 0.03
  }
}