{
  "profil": {
    "kode": "OBAT",
    "nama": "Brigit Biofarmaka Teknologi Tbk",
    "sektor": "Consumer Defensive",
    "sub_sektor": "Packaged Foods",
    "deskripsi_bisnis": "PT Brigit Biofarmaka Technologi Tbk provides manufacturing services for herbal medicine, herbal honey, skincare, cosmetics, botanical tea, and functional powdered drinks in Indonesia. It also offers hair care products, including shampoo, conditioner, hair mask, hair tonic, hair oil, and hair serum and powder, as well as body moisturizer, body cleanser, facial cleanser, moisturizer, essence and serum, face mask, and personal care products. In addition, it provides lip gloss, cushion, foundation, eyeliner, and blush on balm. The company was founded in 2015 and is based in Sukoharjo, Indonesia.",
    "manajemen": "",
    "keunggulan_kompetitif": "",
    "prospek_industri": "",
    "berita_terkini": ""
  },
  "laporan": [],
  "pasar": {
    "harga_saham": 242.0,
    "saham_beredar": 600000000.0,
    "per_sektor": null,
    "pbv_sektor": null,
    "mean_per_3y": null,
    "mean_pbv_3y": null,
    "growth_rate": 0.08,
    "discount_rate": 0.11,
    "terminal_growth": 0.03,
    "tahun_proyeksi": 5,
    "dividend_yield": 0.0311900826446281,
    "dividen_per_saham": 7.548,
    "dividen_beruntun": 2
  }
}