{
  "profil": {
    "kode": "PSGO",
    "nama": "PT Palma Serasih Tbk",
    "sektor": "Consumer Defensive",
    "sub_sektor": "Farm Products",
    "deskripsi_bisnis": "PT Palma Serasih Tbk, through its subsidiaries, engages in the palm oil plantation and processing business in Indonesia. The company also provides construction and trading services. It also exports its products. The company was founded in 2008 and is headquartered in Jakarta Selatan, Indonesia.",
    "manajemen": "",
    "keunggulan_kompetitif": "",
    "prospek_industri": "",
    "berita_terkini": ""
  },
  "laporan": [
    {
      "tahun": 2022,
      "total_aset": 4140857067187.0,
      "aset_lancar": 1304904227804.0,
      "total_liabilitas": 2454764947737.0,
      "liabilitas_lancar": 650908995178.0,
      "total_ekuitas": 1685800077181.0,
      "pendapatan": 1972824875264.0,
      "laba_kotor": 564308990325.0,
      "laba_operasi": 449380489281.0,
      "laba_bersih": 257682090851.0,
      "arus_kas_operasi": 0.0,
      "arus_kas_investasi": 22503788566.0,
      "arus_kas_pendanaan": -117465834583.0
    },
    {
      "tahun": 2023,
      "total_aset": 4181183763101.0,
      "aset_lancar": 1865395461793.0,
      "total_liabilitas": 1944063067826.0,
      "liabilitas_lancar": 673506196655.0,
      "total_ekuitas": 2236818899009.0,
      "pendapatan": 2049487832334.0,
      "laba_kotor": 569397711494.0,
      "laba_operasi": 401616268601.0,
      "laba_bersih": 549244217016.0,
      "arus_kas_operasi": 0.0,
      "arus_kas_investasi": 420052370095.0,
      "arus_kas_pendanaan": -333076299618.0
    },
    {
      "tahun": 2024,
      "total_aset": 3950324909015.0,
      "aset_lancar": 1623238575978.0,
      "total_liabilitas": 1509614343486.0,
      "liabilitas_lancar": 581639479501.0,
      "total_ekuitas": 2440408684341.0,
      "pendapatan": 2127994680911.0,
      "laba_kotor": 663945544865.0,
      "laba_operasi": 494987941675.0,
      "laba_bersih": 350647372618.0,
      "arus_kas_operasi": 0.0,
      "arus_kas_investasi": -144927431231.0,
      "arus_kas_pendanaan": -619105560066.0
    },
    {
      "tahun": 2025,
      "total_aset": 3995296751901.0,
      "aset_lancar": 1668085378583.0,
      "total_liabilitas": 1265250446552.0,
      "liabilitas_lancar": 559883224646.0,
      "total_ekuitas": 2729734477872.0,
      "pendapatan": 2552818121689.0,
      "laba_kotor": 790901681749.0,
      "laba_operasi": 579725340343.0,
      "laba_bersih": 442848958529.0,
      "arus_kas_operasi": 0.0,
      "arus_kas_investasi": -154724874244.0,
      "arus_kas_pendanaan": -454810078992.0
    }
  ],
  "pasar": {
    "harga_saham": 199.0,
    "saham_beredar": 18850000000.0,
    "per_sektor": null,
    "pbv_sektor": null,
    "mean_per_3y": null,
    "mean_pbv_3y": null,
    "growth_rate": 0.08,
    "discount_rate": 0.11,
    "terminal_growth": 0.03,
    "tahun_proyeksi": 5
  }
}