{
  "profil": {
    "kode": "PTPW",
    "nama": "PT Pratama Widya Tbk",
    "sektor": "Industrials",
    "sub_sektor": "Engineering & Construction",
    "deskripsi_bisnis": "PT Pratama Widya Tbk, together with its subsidiaries, provides geotechnical engineering services to the private and government sectors in Indonesia. It operates through Construction Revenue, Trading, and Accommodation segments. The company offers geotechnical investigation services; foundation services comprising bored piles, piling, injection piles, and loading tests; retaining wall services consisting of soldier piles, contiguous piles, sheet piles, secant piles, and diaphragm walls; grouting, jet grouting, deep mixing, and soil cement stabilization services; and slope reinforcement and dewatering services, such as soil nailing, shotcretes, ground anchors, rock bolts, and deep watering services. It also engages in the wholesale trade of building materials and metal goods for construction materials; manufacture of goods from cement and lime for construction; mortar and ready-mix concrete; accommodation; and real estate activities. PT Pratama Widya Tbk was founded in 1981 and is headquartered in Tangerang, Indonesia.",
    "manajemen": "",
    "keunggulan_kompetitif": "",
    "prospek_industri": "",
    "berita_terkini": ""
  },
  "laporan": [],
  "pasar": {
    "harga_saham": 1120.0,
    "saham_beredar": 878187500.0,
    "per_sektor": null,
    "pbv_sektor": null,
    "mean_per_3y": null,
    "mean_pbv_3y": null,
    "growth_rate": 0.08,
    "discount_rate": 0.11,
    "terminal_growth": 0.03,
    "tahun_proyeksi": 5,
    "dividend_yield": 0.00492987012987013,
    "dividen_per_saham": 5.694,
    "dividen_beruntun": 2
  },
  "backtest": {
    "s1": {
      "sinyal": 5,
      "menang": 0,
      "hit3": 0,
      "ret_total": -0.020488958667540514,
      "sinyal_terakhir": false
    },
    "s2": {
      "sinyal": 1,
      "menang": 1,
      "hit3": 0,
      "ret_total": 0.002695400441139462,
      "sinyal_terakhir": false
    },
    "s_and": {
      "sinyal": 0,
      "menang": 0,
      "hit3": 0,
      "ret_total": 0.0,
      "sinyal_terakhir": false
    },
    "s_or": {
      "sinyal": 6,
      "menang": 1,
      "hit3": 0,
      "ret_total": -0.01779355822640105,
      "sinyal_terakhir": false
    }
  },
  "harian": {
    "sampel_hari": 252,
    "peluang_naik_target": 0.0,
    "win_rate": 0.5396825396825397,
    "rata_gap": 0.0006858421980024525,
    "median_gap": 0.004842622506202649,
    "rata_gap_positif": 0.005337255052773503,
    "volatilitas_gap": 0.005246221279230435,
    "volume_rata": 150085.77075098813,
    "target": 0.03
  }
}