{
  "profil": {
    "kode": "RELF",
    "nama": "PT Graha Mitra Asia Tbk",
    "sektor": "Real Estate",
    "sub_sektor": "Real Estate - Development",
    "deskripsi_bisnis": "PT Graha Mitra Asia Tbk provides real estate and property development services in Indonesia. The company provides real estate agency, real estate brokers, and intermediaries for buying, selling, leasing real estate on a fee or contract basis; real estate management services; and real estate appraisal services, as well as real estate probate agent services. PT Graha Mitra Asia Tbk was founded in 2018 and is headquartered in Bogor, Indonesia.",
    "manajemen": "",
    "keunggulan_kompetitif": "",
    "prospek_industri": "",
    "berita_terkini": ""
  },
  "laporan": [],
  "pasar": {
    "harga_saham": 33.0,
    "saham_beredar": 5727832195.0,
    "per_sektor": null,
    "pbv_sektor": null,
    "mean_per_3y": null,
    "mean_pbv_3y": null,
    "growth_rate": 0.08,
    "discount_rate": 0.11,
    "terminal_growth": 0.03,
    "tahun_proyeksi": 5,
    "dividend_yield": 0.006666666666666667,
    "dividen_per_saham": 0.22,
    "dividen_beruntun": 3
  },
  "backtest": {
    "s1": {
      "sinyal": 0,
      "menang": 0,
      "hit3": 0,
      "ret_total": 0.0,
      "sinyal_terakhir": false
    },
    "s2": {
      "sinyal": 8,
      "menang": 8,
      "hit3": 4,
      "ret_total": 0.29044587632704316,
      "sinyal_terakhir": false
    },
    "s_and": {
      "sinyal": 0,
      "menang": 0,
      "hit3": 0,
      "ret_total": 0.0,
      "sinyal_terakhir": false
    },
    "s_or": {
      "sinyal": 8,
      "menang": 8,
      "hit3": 4,
      "ret_total": 0.29044587632704316,
      "sinyal_terakhir": false
    }
  },
  "harian": {
    "sampel_hari": 252,
    "peluang_naik_target": 0.1111111111111111,
    "win_rate": 0.2777777777777778,
    "rata_gap": 0.0008782732572166431,
    "median_gap": 0.0,
    "rata_gap_positif": 0.03382634332653226,
    "volatilitas_gap": 0.031601673229891845,
    "volume_rata": 18134339.5256917,
    "target": 0.03
  }
}