{
  "profil": {
    "kode": "TRON",
    "nama": "PT Teknologi Karya Digital Nusa Tbk",
    "sektor": "Technology",
    "sub_sektor": "Information Technology Services",
    "deskripsi_bisnis": "PT Teknologi Karya Digital Nusa Tbk engages in the IT transportation telematics and systems development activities to passenger and freight transportation industries in Indonesia. The company provides safety fleet management system, public transport and logistic solutions, intelligent traffic control system, Internet of Things (IoT) smart bus, tourism solutions, smart street lighting, digital payment solutions, transit-oriented development, terminal operating system, smart command center, railways monitoring solutions, identification and booking system, maintenance and LiDAR system. It also offers Software as a Service solution, including transit management, project management, and smart parking; and telematic smart devices for public transport, maritime and mining sector. In addition, the company provides business process outsourcing, which includes customer service management, human resources, information technology systems, and real-time performance reporting; three-wheel electric vehicle solutions; revolutionizing transportation; battery electric vehicle; new energy vehicle; battery energy storage system; and charging facilities for electric vehicles. PT Teknologi Karya Digital Nusa Tbk was founded in 2011 and is headquartered in Jakarta Utara, Indonesia.",
    "manajemen": "",
    "keunggulan_kompetitif": "",
    "prospek_industri": "",
    "berita_terkini": ""
  },
  "laporan": [],
  "pasar": {
    "harga_saham": 110.0,
    "saham_beredar": 2951328448.0,
    "per_sektor": null,
    "pbv_sektor": null,
    "mean_per_3y": null,
    "mean_pbv_3y": null,
    "growth_rate": 0.08,
    "discount_rate": 0.11,
    "terminal_growth": 0.03,
    "tahun_proyeksi": 5,
    "dividend_yield": null,
    "dividen_per_saham": null,
    "dividen_beruntun": 0
  },
  "backtest": {
    "s1": {
      "sinyal": 6,
      "menang": 0,
      "hit3": 0,
      "ret_total": -0.024390243902439025,
      "sinyal_terakhir": false
    },
    "s2": {
      "sinyal": 5,
      "menang": 5,
      "hit3": 4,
      "ret_total": 0.4541715241535622,
      "sinyal_terakhir": false
    },
    "s3": {
      "sinyal": 9,
      "menang": 7,
      "hit3": 3,
      "ret_total": 0.268675821356345,
      "sinyal_terakhir": false
    },
    "s_and": {
      "sinyal": 0,
      "menang": 0,
      "hit3": 0,
      "ret_total": 0.0,
      "sinyal_terakhir": false
    },
    "s_or": {
      "sinyal": 11,
      "menang": 5,
      "hit3": 4,
      "ret_total": 0.42978128025112317,
      "sinyal_terakhir": false
    }
  },
  "harian": {
    "sampel_hari": 252,
    "peluang_naik_target": 0.08333333333333333,
    "win_rate": 0.45634920634920634,
    "rata_gap": 0.006553982030297978,
    "median_gap": 0.0,
    "rata_gap_positif": 0.025137115080122143,
    "volatilitas_gap": 0.03718602238942106,
    "volume_rata": 31137462.05533597,
    "target": 0.03
  }
}