{
  "profil": {
    "kode": "TYRE",
    "nama": "PT King Tire Indonesia Tbk",
    "sektor": "Consumer Cyclical",
    "sub_sektor": "Auto Parts",
    "deskripsi_bisnis": "PT King Tire Indonesia Tbk manufactures and sells tubes and tires in Indonesia. It offers tubes and tires for bicycles and motorcycles. The company was founded in 1977 and is based in Serang, Indonesia.",
    "manajemen": "",
    "keunggulan_kompetitif": "",
    "prospek_industri": "",
    "berita_terkini": ""
  },
  "laporan": [],
  "pasar": {
    "harga_saham": 117.0,
    "saham_beredar": 3478020000.0,
    "per_sektor": null,
    "pbv_sektor": null,
    "mean_per_3y": null,
    "mean_pbv_3y": null,
    "growth_rate": 0.08,
    "discount_rate": 0.11,
    "terminal_growth": 0.03,
    "tahun_proyeksi": 5,
    "dividend_yield": 0.017094017094017096,
    "dividen_per_saham": 2.0,
    "dividen_beruntun": 1
  }
}